gpioemu.v
/* verilator lint_off UNUSED */
/* verilator lint_off MULTIDRIVEN */
/* verilator lint_off UNDRIVEN */
/* verilator lint_off COMBDLY */
/* verilator lint_off WIDTH */
/* verilator lint_off BLKSEQ */
/* verilator lint_off BLKANDNBLK */

module gpioemu(                             //magistrala z CPU
    n_reset,
    saddress[15:0], srd, swr,                           
    sdata_in[31:0], sdata_out[31:0], 
    gpio_in[31:0], gpio_latch,          	//styk z GPIO - in                          
    gpio_out[31:0],                     	//styk z GPIO - out
    clk,                                	//sygnal zegara
    gpio_in_s_insp[31:0]);                  //sygnał testowy

    input 			clk;
	input 			n_reset;
	input 	[15:0] 	saddress;               //magistrala adresów
	input 			srd;                    //odczyt przez CPU z mag. danych
	input 			swr;                    //zapis przez CPU do mag. danych
	input	[31:0] 	sdata_in;               //magistrala wejściowa CPU
	input 	[31:0] 	gpio_in;                //dane z peryferii wejście do modulu
	input			gpio_latch;             //zapis danych na gpio_in

	output 	[31:0] 	sdata_out;              //magistrala wyjściowa z CPU
	output	[31:0] 	gpio_out;               //dane wyjsciowe do peryferii
    output  [31:0]  gpio_in_s_insp;         //debuging

	reg 	[31:0] 	gpio_in_s;           	//stan peryferii wyjsciowych
	reg 	[31:0] 	gpio_out_s;          	//stan peryferii wejsciowych    
	
	reg		[31:0] 	sdata_out_s;      	    //stan magistrali danych - wyjscie
	reg     [15:0]  counter;             	//licznik wykonanych operacji  
	reg     [23:0]  A1;                  	//rejestr zawierajacy pierwsza liczbe
    reg     [23:0]  A2;                  	//rejestr zawierajacy druga liczbe
    reg     [31:0]  W;                   	//wynik operacji mnozenia
    reg     [5:0]   L;              	    //liczba jedynek w wyniku (max 32 jedynki = wystarczy 6 bitow)
    reg     [31:0]  B;                   	//stan zleconej operacji(
    
    reg     [47:0]  result;                  //rejestr pomocniczy 

    
    
	integer i = 0;
	integer j = 0;

	assign sdata_out = sdata_out_s;
	assign gpio_out = gpio_out_s;
    assign gpio_in_s_insp = gpio_in_s;


	always @(negedge n_reset) 
	begin
		counter <= 16'h0;
		gpio_out_s <= 0;
        A1 <= 0;
        A2 <= 0;
        W <= 0;
        B <= 0;
        L <= 0;
        result <= 0;
		i <= 0;
		j <= 0;
        
        
	end
	always @(posedge clk) begin
            if (B == 1) // jelsi B ==1 następuje rozpoaczęcie operacji możenia
		begin
			result <= 0;
			for (i = 0; i < 23; i = i + 1) begin   
                if (A2[i] == 1) begin
                    result = result + (A1 << i);
                end
			end
			for (j = 0; j < 47; j = j + 1) begin
                     if (result[j] == 1) begin
                         L = L + 1;
					 end

			if (result > 2**32 - 1) 
			begin
				B <= 2; // B = 2 oznacza to błąd
				i <= 0;
				j <= 0;
				L <= 6'h0;
				
			end 
			else begin
				B <= 0; 
				i <= 0;
				j <= 0;
				
				W <= result;
				counter <= counter + 1;
			end
            end
		end
    end

	// odczyt z szyny gpio_in po sygnale gpio_latch
		
	always @(posedge gpio_latch)
	begin
		gpio_in_s <= gpio_in;
	end
			
	// odczyt danych z magistrali	
    always @(posedge srd) begin
        case (saddress)
            16'h100: sdata_out_s[31:0] <= {8'h0, A1};
            16'h108: sdata_out_s[31:0] <= {8'h0, A2};
            16'h110: sdata_out_s <= W;
            16'h120: sdata_out_s <= B;
            16'h118: sdata_out_s <= {26'h0, L};
			16'h130: sdata_out_s <= {16'h0, counter [15:0]};

            default: sdata_out_s <= 32'h0;
        endcase
    end
		
	// zapis danych do magistrali
    always @(posedge swr) begin
        if (saddress == 16'h100) begin
				A1 <= sdata_in[23:0];
		end
		else if (saddress == 16'h108) begin
				A2 <= sdata_in[23:0];
				L <= 6'h0;
				if (B == 0) begin 
					B <= 1;
				end
		end
    end
		
		
endmodule

gpioemu_tb.v
`timescale 1ns/10ps

module gpioemu_tb;

  // Inputs
  reg clk;
  reg n_reset;
  reg [15:0] saddress;
  reg srd;
  reg swr;
  reg [31:0] sdata_in;
  reg [31:0] gpio_in;
  reg gpio_latch;

  // Outputs
  wire [31:0] sdata_out;
  wire [31:0] gpio_out;
  wire [31:0] gpio_in_s_insp;


  // Instancja testowa
  gpioemu gpioemu (
    n_reset,
    saddress,
    srd,
    swr,
    sdata_in,
    sdata_out,
    gpio_in,
    gpio_latch,
    gpio_out,
    clk,
    gpio_in_s_insp
  );

  initial begin
	$dumpfile("gpioemu.vcd");
	$dumpvars(0,gpioemu_tb);
	end

  // Generacja zegara
  initial begin
    clk = 0;
    forever #5 clk = ~clk;
  end

  initial begin
    // Inicjalizacja inputów
    n_reset = 0;
    saddress = 16'h0;
    srd = 0;
    swr = 0;
    sdata_in = 32'h0;
    gpio_in = 32'h0;
    gpio_latch = 0;
    #10;

    #5 n_reset = 1;

    // ustawienie wartosci
	  #5 sdata_in = 24'hface;
	  #5 gpio_latch = 1;
    #5
	  #5 gpio_latch = 0;
    #10

    // Zapis do rejestru A1
    #5 saddress = 16'h100;
    #5 swr = 1;
    #5
    #5 swr = 0;
    #10;

    // Odczyt z rejestru A1
    #5 saddress = 16'h100;
    #5 srd = 1;
    #5
    #5 srd = 0;
    #10;

    // zmiana wartosci
	  #5 sdata_in = 24'hff;
	  #5 gpio_latch = 1;
    #5
	  #5 gpio_latch = 0;
    #10

    // Zapis do rejestru A2 --- pierwsze mnozenie
    #5 saddress = 16'h108;
    #5 swr = 1;
    #5
    #5 swr = 0;
    #10;
    
    // Odczyt z rejestru A2
    #5 saddress = 16'h108;
    #5 srd = 1;
    #5
    #5 srd = 0;
    #10;

    // Odczyt z rejestru B
    #5 saddress = 16'h120;
    #5 srd = 1;
    #5
    #5 srd = 0;
    #10;

    #100;

    // Odczyt z rejestru W
    #5 saddress = 16'h110;
    #5 srd = 1;
    #5
    #5 srd = 0;
    #10;

    // Odczyt z rejestru licznika operacji
    #5 saddress = 16'h130;
    #5 srd = 1;
    #5
    #5 srd = 0;
    #10;
	
	// ustawienie wartosci
	  #5 sdata_in = 24'hba5;
	  #5 gpio_latch = 1;
    #5
	  #5 gpio_latch = 0;
    #10

    // Zapis do rejestru A1
    #5 saddress = 16'h100;
    #5 swr = 1;
    #5
    #5 swr = 0;
    #10;

    // Odczyt z rejestru A1
    #5 saddress = 16'h100;
    #5 srd = 1;
    #5
    #5 srd = 0;
    #10;

    // zmiana wartosci
	  #5 sdata_in = 24'h0;
	  #5 gpio_latch = 1;
    #5
	  #5 gpio_latch = 0;
    #10

    // Zapis do rejestru A2 --- drugie mnozenie
    #5 saddress = 16'h108;
    #5 swr = 1;
    #5
    #5 swr = 0;
    #10;
    
    // Odczyt z rejestru A2
    #5 saddress = 16'h108;
    #5 srd = 1;
    #5
    #5 srd = 0;
    #10;
	 
	 // Odczyt z rejestru B
    #5 saddress = 16'h120;
    #5 srd = 1;
    #5
    #5 srd = 0;
    #10;

    #100;

    // Odczyt z rejestru W
    #5 saddress = 16'h110;
    #5 srd = 1;
    #5
    #5 srd = 0;
    #10;

    // Odczyt z rejestru licznika operacji
    #5 saddress = 16'h130;
    #5 srd = 1;
    #5
    #5 srd = 0;
    #10;
	
	// ustawienie wartosci
	  #5 sdata_in = 24'hface;
	  #5 gpio_latch = 1;
    #5
	  #5 gpio_latch = 0;
    #10

    // Zapis do rejestru A1
    #5 saddress = 16'h100;
    #5 swr = 1;
    #5
    #5 swr = 0;
    #10;

    // Odczyt z rejestru A1
    #5 saddress = 16'h100;
    #5 srd = 1;
    #5
    #5 srd = 0;
    #10;

    // zmiana wartosci
	  #5 sdata_in = 24'h1;
	  #5 gpio_latch = 1;
    #5
	  #5 gpio_latch = 0;
    #10

    // Zapis do rejestru A2 --- trzecie mnozenie
    #5 saddress = 16'h108;
    #5 swr = 1;
    #5
    #5 swr = 0;
    #10;
    
    // Odczyt z rejestru A2
    #5 saddress = 16'h108;
    #5 srd = 1;
    #5
    #5 srd = 0;
    #10;
	 
	 // Odczyt z rejestru B
    #5 saddress = 16'h120;
    #5 srd = 1;
    #5
    #5 srd = 0;
    #10;

    #100;

    // Odczyt z rejestru W
    #5 saddress = 16'h110;
    #5 srd = 1;
    #5
    #5 srd = 0;
    #10;

    // Odczyt z rejestru licznika operacji
    #5 saddress = 16'h130;
    #5 srd = 1;
    #5
    #5 srd = 0;
    #10;

    // ustawienie wartosci
	  #5 sdata_in = 24'hf9f8f7;
	  #5 gpio_latch = 1;
    #5
	  #5 gpio_latch = 0;
    #10

    // Zapis do rejestru A1
    #5 saddress = 16'h100;
    #5 swr = 1;
    #5
    #5 swr = 0;
    #10;

    // Odczyt z rejestru A1
    #5 saddress = 16'h100;
    #5 srd = 1;
    #5
    #5 srd = 0;
    #10;

    // zmiana wartosci
	  #5 sdata_in = 24'hf1f2f3;
	  #5 gpio_latch = 1;
    #5
	  #5 gpio_latch = 0;
    #10

    // Zapis do rejestru A2 --- czwarte mnozenie
    #5 saddress = 16'h108;
    #5 swr = 1;
    #5
    #5 swr = 0;
    #100;

    $finish;
  end

endmodule

gpioemu.vcd
$date
	Sat Jun 03 14:49:57 2023
$end
$version
	Icarus Verilog
$end
$timescale
	10ps
$end
$scope module gpioemu_tb $end
$var wire 32 ! sdata_out [31:0] $end
$var wire 32 " gpio_out [31:0] $end
$var wire 32 # gpio_in_s_insp [31:0] $end
$var reg 1 $ clk $end
$var reg 32 % gpio_in [31:0] $end
$var reg 1 & gpio_latch $end
$var reg 1 ' n_reset $end
$var reg 16 ( saddress [15:0] $end
$var reg 32 ) sdata_in [31:0] $end
$var reg 1 * srd $end
$var reg 1 + swr $end
$scope module gpioemu $end
$var wire 1 $ clk $end
$var wire 32 , gpio_in [31:0] $end
$var wire 32 - gpio_in_s_insp [31:0] $end
$var wire 1 & gpio_latch $end
$var wire 32 . gpio_out [31:0] $end
$var wire 1 ' n_reset $end
$var wire 16 / saddress [15:0] $end
$var wire 32 0 sdata_in [31:0] $end
$var wire 32 1 sdata_out [31:0] $end
$var wire 1 * srd $end
$var wire 1 + swr $end
$var reg 24 2 A1 [23:0] $end
$var reg 24 3 A2 [23:0] $end
$var reg 32 4 B [31:0] $end
$var reg 6 5 L [5:0] $end
$var reg 32 6 W [31:0] $end
$var reg 16 7 counter [15:0] $end
$var reg 32 8 gpio_in_s [31:0] $end
$var reg 32 9 gpio_out_s [31:0] $end
$var reg 48 : result [47:0] $end
$var reg 32 ; sdata_out_s [31:0] $end
$var integer 32 < i [31:0] $end
$var integer 32 = j [31:0] $end
$upscope $end
$upscope $end
$enddefinitions $end
$comment Show the parameter values. $end
$dumpall
$end
#0
$dumpvars
b0 =
b0 <
bx ;
b0 :
b0 9
bx 8
b0 7
b0 6
b0 5
b0 4
b0 3
b0 2
bx 1
b0 0
b0 /
b0 .
bx -
b0 ,
0+
0*
b0 )
b0 (
0'
0&
b0 %
0$
bx #
b0 "
bx !
$end
#500
1$
#1000
0$
#1500
1$
1'
#2000
0$
b1111101011001110 )
b1111101011001110 0
#2500
b0 #
b0 -
b0 8
1$
1&
#3000
0$
#3500
1$
0&
#4000
0$
#4500
1$
#5000
0$
b100000000 (
b100000000 /
#5500
b1111101011001110 2
1$
1+
#6000
0$
#6500
1$
0+
#7000
0$
#7500
1$
#8000
0$
#8500
b1111101011001110 !
b1111101011001110 1
b1111101011001110 ;
1$
1*
#9000
0$
#9500
1$
0*
#10000
0$
#10500
1$
#11000
0$
b11111111 )
b11111111 0
#11500
1$
1&
#12000
0$
#12500
1$
0&
#13000
0$
#13500
1$
#14000
0$
b100001000 (
b100001000 /
#14500
b1 4
b11111111 3
1$
1+
#15000
0$
#15500
b1 7
b111110011101001100110010 6
b0 4
b1110 5
b0 =
b0 <
b0 :
1$
0+
#16000
0$
#16500
1$
#17000
0$
#17500
b11111111 !
b11111111 1
b11111111 ;
1$
1*
#18000
0$
#18500
1$
0*
#19000
0$
#19500
1$
#20000
0$
b100100000 (
b100100000 /
#20500
b0 !
b0 1
b0 ;
1$
1*
#21000
0$
#21500
1$
0*
#22000
0$
#22500
1$
#23000
0$
#23500
1$
#24000
0$
#24500
1$
#25000
0$
#25500
1$
#26000
0$
#26500
1$
#27000
0$
#27500
1$
#28000
0$
#28500
1$
#29000
0$
#29500
1$
#30000
0$
#30500
1$
#31000
0$
#31500
1$
#32000
0$
#32500
1$
#33000
0$
b100010000 (
b100010000 /
#33500
b111110011101001100110010 !
b111110011101001100110010 1
b111110011101001100110010 ;
1$
1*
#34000
0$
#34500
1$
0*
#35000
0$
#35500
1$
#36000
0$
b100110000 (
b100110000 /
#36500
b1 !
b1 1
b1 ;
1$
1*
#37000
0$
#37500
1$
0*
#38000
0$
#38500
1$
#39000
0$
b101110100101 )
b101110100101 0
#39500
1$
1&
#40000
0$
#40500
1$
0&
#41000
0$
#41500
1$
#42000
0$
b100000000 (
b100000000 /
#42500
b101110100101 2
1$
1+
#43000
0$
#43500
1$
0+
#44000
0$
#44500
1$
#45000
0$
#45500
b101110100101 !
b101110100101 1
b101110100101 ;
1$
1*
#46000
0$
#46500
1$
0*
#47000
0$
#47500
1$
#48000
0$
b0 )
b0 0
#48500
1$
1&
#49000
0$
#49500
1$
0&
#50000
0$
#50500
1$
#51000
0$
b100001000 (
b100001000 /
#51500
b1 4
b0 5
b0 3
1$
1+
#52000
0$
#52500
b10 7
b0 6
b0 4
b0 =
b0 <
1$
0+
#53000
0$
#53500
1$
#54000
0$
#54500
b0 !
b0 1
b0 ;
1$
1*
#55000
0$
#55500
1$
0*
#56000
0$
#56500
1$
#57000
0$
b100100000 (
b100100000 /
#57500
1$
1*
#58000
0$
#58500
1$
0*
#59000
0$
#59500
1$
#60000
0$
#60500
1$
#61000
0$
#61500
1$
#62000
0$
#62500
1$
#63000
0$
#63500
1$
#64000
0$
#64500
1$
#65000
0$
#65500
1$
#66000
0$
#66500
1$
#67000
0$
#67500
1$
#68000
0$
#68500
1$
#69000
0$
#69500
1$
#70000
0$
b100010000 (
b100010000 /
#70500
1$
1*
#71000
0$
#71500
1$
0*
#72000
0$
#72500
1$
#73000
0$
b100110000 (
b100110000 /
#73500
b10 !
b10 1
b10 ;
1$
1*
#74000
0$
#74500
1$
0*
#75000
0$
#75500
1$
#76000
0$
b1111101011001110 )
b1111101011001110 0
#76500
1$
1&
#77000
0$
#77500
1$
0&
#78000
0$
#78500
1$
#79000
0$
b100000000 (
b100000000 /
#79500
b1111101011001110 2
1$
1+
#80000
0$
#80500
1$
0+
#81000
0$
#81500
1$
#82000
0$
#82500
b1111101011001110 !
b1111101011001110 1
b1111101011001110 ;
1$
1*
#83000
0$
#83500
1$
0*
#84000
0$
#84500
1$
#85000
0$
b1 )
b1 0
#85500
1$
1&
#86000
0$
#86500
1$
0&
#87000
0$
#87500
1$
#88000
0$
b100001000 (
b100001000 /
#88500
b1 4
b1 3
1$
1+
#89000
0$
#89500
b11 7
b1111101011001110 6
b0 4
b1011 5
b0 =
b0 <
b0 :
1$
0+
#90000
0$
#90500
1$
#91000
0$
#91500
b1 !
b1 1
b1 ;
1$
1*
#92000
0$
#92500
1$
0*
#93000
0$
#93500
1$
#94000
0$
b100100000 (
b100100000 /
#94500
b0 !
b0 1
b0 ;
1$
1*
#95000
0$
#95500
1$
0*
#96000
0$
#96500
1$
#97000
0$
#97500
1$
#98000
0$
#98500
1$
#99000
0$
#99500
1$
#100000
0$
#100500
1$
#101000
0$
#101500
1$
#102000
0$
#102500
1$
#103000
0$
#103500
1$
#104000
0$
#104500
1$
#105000
0$
#105500
1$
#106000
0$
#106500
1$
#107000
0$
b100010000 (
b100010000 /
#107500
b1111101011001110 !
b1111101011001110 1
b1111101011001110 ;
1$
1*
#108000
0$
#108500
1$
0*
#109000
0$
#109500
1$
#110000
0$
b100110000 (
b100110000 /
#110500
b11 !
b11 1
b11 ;
1$
1*
#111000
0$
#111500
1$
0*
#112000
0$
#112500
1$
#113000
0$
b111110011111100011110111 )
b111110011111100011110111 0
#113500
1$
1&
#114000
0$
#114500
1$
0&
#115000
0$
#115500
1$
#116000
0$
b100000000 (
b100000000 /
#116500
b111110011111100011110111 2
1$
1+
#117000
0$
#117500
1$
0+
#118000
0$
#118500
1$
#119000
0$
#119500
b111110011111100011110111 !
b111110011111100011110111 1
b111110011111100011110111 ;
1$
1*
#120000
0$
#120500
1$
0*
#121000
0$
#121500
1$
#122000
0$
b111100011111001011110011 )
b111100011111001011110011 0
#122500
1$
1&
#123000
0$
#123500
1$
0&
#124000
0$
#124500
1$
#125000
0$
b100001000 (
b100001000 /
#125500
b1 4
b0 5
b111100011111001011110011 3
1$
1+
#126000
0$
#126500
b10 4
b0 =
b0 5
b0 <
b0 :
1$
0+
